cmsdials/__init__.py
cmsdials/_version.py
cmsdials/cmsdials.py
cmsdials/filters.py
cmsdials/auth/__init__.py
cmsdials/auth/_base.py
cmsdials/auth/bearer.py
cmsdials/auth/client.py
cmsdials/auth/exceptions.py
cmsdials/auth/models.py
cmsdials/auth/secret_key.py
cmsdials/clients/__init__.py
cmsdials/clients/dataset_index/__init__.py
cmsdials/clients/dataset_index/client.py
cmsdials/clients/dataset_index/models.py
cmsdials/clients/file_index/__init__.py
cmsdials/clients/file_index/client.py
cmsdials/clients/file_index/models.py
cmsdials/clients/h1d/__init__.py
cmsdials/clients/h1d/client.py
cmsdials/clients/h1d/models.py
cmsdials/clients/h2d/__init__.py
cmsdials/clients/h2d/client.py
cmsdials/clients/h2d/models.py
cmsdials/clients/lumisection/__init__.py
cmsdials/clients/lumisection/client.py
cmsdials/clients/lumisection/models.py
cmsdials/clients/mes/__init__.py
cmsdials/clients/mes/client.py
cmsdials/clients/mes/models.py
cmsdials/clients/ml_bad_lumisection/__init__.py
cmsdials/clients/ml_bad_lumisection/client.py
cmsdials/clients/ml_bad_lumisection/models.py
cmsdials/clients/ml_models_index/__init__.py
cmsdials/clients/ml_models_index/client.py
cmsdials/clients/ml_models_index/models.py
cmsdials/clients/oms_proxy/__init__.py
cmsdials/clients/oms_proxy/client.py
cmsdials/clients/oms_proxy/models.py
cmsdials/clients/run/__init__.py
cmsdials/clients/run/client.py
cmsdials/clients/run/models.py
cmsdials/clients/workspace/__init__.py
cmsdials/clients/workspace/client.py
cmsdials/utils/__init__.py
cmsdials/utils/_json.py
cmsdials/utils/api_client.py
cmsdials/utils/base_model.py
cmsdials/utils/logger.py
cmsdials-2.0.0.dist-info/licenses/LICENSE
cmsdials-2.0.0.dist-info/METADATA
cmsdials-2.0.0.dist-info/WHEEL
cmsdials-2.0.0.dist-info/top_level.txt
cmsdials-2.0.0.dist-info/RECORD
