Metadata-Version: 2.4
Name: cmsdials
Version: 2.0.0
Summary: The Python api client interface to DIALS service
Author-email: Gabriel Moreira <gabriel.moreira@cern.ch>
Project-URL: Repository, https://gitlab.cern.ch/cms-dqmdc/libraries/dials-py
Classifier: Development Status :: 5 - Production/Stable
Classifier: Programming Language :: Python :: 3.9
Classifier: Programming Language :: Python :: 3.10
Classifier: Programming Language :: Python :: 3.11
Classifier: Programming Language :: Python :: 3.12
Requires-Python: >=3.9
License-File: LICENSE
Requires-Dist: requests<3.0.0,>=2.31.0
Requires-Dist: urllib3<2.0.0,>=1.26.16
Requires-Dist: pydantic<3.0.0,>=2.8.2
Provides-Extra: pandas
Requires-Dist: pandas>=1.5.3; extra == "pandas"
Provides-Extra: tqdm
Requires-Dist: tqdm>=4.66.1; extra == "tqdm"
Dynamic: license-file
